{"id":50546,"imdb_id":"tt1564367","overview":"A plastic surgeon, romancing a much younger schoolteacher, enlists his loyal assistant to pretend to be his soon to be ex-wife, in order to cover up a careless lie. When more lies backfire, the assistant's kids become involved, and everyone heads off for a weekend in Hawaii that will change all their lives.","poster_path":"/4sJDqzBaqBprkEy0aLjIGl7TrHx.jpg","runtime":117,"title":"Just Go with It","year":"2011-02-10","cast":["Adam Sandler","Jennifer Aniston","Nicole Kidman"]}