{"id":24253,"imdb_id":"tt1216487","overview":"Mikael Blomkvist, publisher of Millennium magazine, has made his living exposing the crooked and corrupt practices of establishment Swedish figures. So when a young journalist approaches him with a meticulously researched thesis about sex trafficking in Sweden and those in high office who abuse underage girls, Blomkvist immediately throws himself into the investigation.","poster_path":"/A7mtwVCduh0VyKDV6hLqXH9d1jW.jpg","runtime":129,"title":"The Girl Who Played with Fire","year":"2009-09-18","cast":["Michael Nyqvist","Noomi Rapace","Lena Endre"]}