{"id":48171,"imdb_id":"tt1161864","overview":"Seminary student Michael Kovak (Colin O'Donoghue) reluctantly attends exorcism school at the Vatican. While he’s in Rome, Michael meets an unorthodox priest, Father Lucas (Anthony Hopkins), who introduces him to the darker side of his faith, uncovering the devil’s reach even to one of the holiest places on Earth.","poster_path":"/94jKSKAOfM3EU4bPsOPkVB9AOHT.jpg","runtime":114,"title":"The Rite","year":"2011-01-28","cast":["Anthony Hopkins","Colin O'Donoghue","Alice Braga"]}